clearml_serving/__init__.py
clearml_serving/__main__.py
clearml_serving/version.py
clearml_serving/engines/__init__.py
clearml_serving/engines/triton/__init__.py
clearml_serving/engines/triton/triton_helper.py
clearml_serving/serving/__init__.py
clearml_serving/serving/endpoints.py
clearml_serving/serving/init.py
clearml_serving/serving/main.py
clearml_serving/serving/model_request_processor.py
clearml_serving/serving/preprocess_service.py
clearml_serving/serving/utils.py
clearml_serving/serving/uvicorn_mp_entrypoint.py
clearml_serving/statistics/__init__.py
clearml_serving/statistics/main.py
clearml_serving/statistics/metrics.py
clearml_serving-1.3.5.dist-info/LICENSE
clearml_serving-1.3.5.dist-info/METADATA
clearml_serving-1.3.5.dist-info/WHEEL
clearml_serving-1.3.5.dist-info/entry_points.txt
clearml_serving-1.3.5.dist-info/top_level.txt
clearml_serving-1.3.5.dist-info/RECORD
