Metadata-Version: 2.1
Name: clearml-serving
Version: 1.3.5
Summary: clearml-serving - Model-Serving Orchestration and Repository Solution
Home-page: https://github.com/clearml/clearml-serving.git
Author: ClearML
Author-email: support@clear.ml
License: Apache License 2.0
Keywords: clearml mlops devops trains development machine deep learning version control machine-learning machinelearning deeplearning deep-learning model-serving
Platform: UNKNOWN
Classifier: Development Status :: 5 - Production/Stable
Classifier: Intended Audience :: Developers
Classifier: Intended Audience :: Science/Research
Classifier: Operating System :: POSIX :: Linux
Classifier: Operating System :: MacOS :: MacOS X
Classifier: Operating System :: Microsoft
Classifier: Topic :: Scientific/Engineering :: Artificial Intelligence
Classifier: Topic :: Software Development
Classifier: Topic :: Software Development :: Version Control
Classifier: Topic :: System :: Logging
Classifier: Topic :: System :: Monitoring
Classifier: Programming Language :: Python :: 3.6
Classifier: Programming Language :: Python :: 3.7
Classifier: Programming Language :: Python :: 3.8
Classifier: Programming Language :: Python :: 3.9
Classifier: Programming Language :: Python :: 3.10
Classifier: Programming Language :: Python :: 3.11
Classifier: License :: OSI Approved :: Apache Software License
Requires-Dist: clearml (>=1.3.1)
Requires-Dist: pillow (>=10.3.0)
